subgrab/__init__.py
subgrab/cli.py
subgrab/providers/__init__.py
subgrab/providers/subdb.py
subgrab/providers/subscene.py
subgrab/utils/__init__.py
subgrab/utils/directory.py
subgrab/utils/titleparser.py
subgrab-1.0.4.dist-info/entry_points.txt
subgrab-1.0.4.dist-info/WHEEL
subgrab-1.0.4.dist-info/METADATA
subgrab-1.0.4.dist-info/RECORD
